datasette_write/__init__.py
datasette_write/templates/datasette_write.html
datasette_write-0.4.dist-info/METADATA
datasette_write-0.4.dist-info/WHEEL
datasette_write-0.4.dist-info/entry_points.txt
datasette_write-0.4.dist-info/top_level.txt
datasette_write-0.4.dist-info/RECORD
