Metadata-Version: 2.1
Name: datasette-write
Version: 0.4
Summary: Datasette plugin providing a UI for writing to a database
Home-page: https://github.com/simonw/datasette-write
Author: Simon Willison
License: Apache License, Version 2.0
Project-URL: Issues, https://github.com/simonw/datasette-write/issues
Project-URL: CI, https://github.com/simonw/datasette-write/actions
Project-URL: Changelog, https://github.com/simonw/datasette-write/releases
Requires-Dist: datasette >=0.64.6
Provides-Extra: test
Requires-Dist: pytest ; extra == 'test'
Requires-Dist: pytest-asyncio ; extra == 'test'
Requires-Dist: httpx ; extra == 'test'
Requires-Dist: beautifulsoup4 ; extra == 'test'
